server.py
avm_mcp_server-0.1.3.dist-info/METADATA
avm_mcp_server-0.1.3.dist-info/WHEEL
avm_mcp_server-0.1.3.dist-info/entry_points.txt
avm_mcp_server-0.1.3.dist-info/RECORD
