Metadata-Version: 2.4
Name: avm-mcp-server
Version: 0.1.3
Summary: MCP Server for discovering and exploring Azure Verified Modules (AVM)
Project-URL: Homepage, https://github.com/stefanstranger/avm-mcp-server
Project-URL: Repository, https://github.com/stefanstranger/avm-mcp-server
Author: Stefan Stranger
License: MIT
Requires-Python: >=3.10
Requires-Dist: fastmcp
Requires-Dist: requests
